{
	"name": "debugdemo1",
	"properties": {
		"type": "MappingDataFlow",
		"typeProperties": {
			"sources": [
				{
					"dataset": {
						"referenceName": "MoviesD2",
						"type": "DatasetReference"
					},
					"name": "source1"
				}
			],
			"sinks": [
				{
					"dataset": {
						"referenceName": "JsonFolder",
						"type": "DatasetReference"
					},
					"name": "sink1"
				}
			],
			"transformations": [
				{
					"name": "DerivedColumn1"
				}
			],
			"script": "parameters{\n\tparameter1 as string ('abc')\n}\nsource(output(\n\t\tmovie as string,\n\t\ttitle as string,\n\t\tgenres as string,\n\t\tyear as string,\n\t\tRating as string,\n\t\tRottenTomato as string\n\t),\n\tallowSchemaDrift: true,\n\tvalidateSchema: false,\n\tignoreNoFilesFound: false) ~> source1\nsource1 derive(json = $parameter1) ~> DerivedColumn1\nDerivedColumn1 sink(allowSchemaDrift: true,\n\tvalidateSchema: false,\n\tpartitionFileNames:['debug.json'],\n\tpartitionBy('hash', 1),\n\tskipDuplicateMapInputs: true,\n\tskipDuplicateMapOutputs: true) ~> sink1"
		}
	}
}