{
	"name": "pivotflow2",
	"properties": {
		"sources": [
			{
				"dataset": {
					"referenceName": "Product_Blob",
					"type": "DatasetReference"
				},
				"name": "ProductSource",
				"script": "source(output(ProductID as string,Name as string,ProductNumber as string,Color as string,StandardCost as string,ListPrice as string,Size as string,Weight as string,ProductCategoryID as string,ProductModelID as string),allowSchemaDrift: false,validateSchema: false) ~> ProductSource"
			}
		],
		"transformations": [
			{
				"name": "PivotColorStandardCost",
				"script": "ProductSource pivot(groupBy(Name, ProductID), pivotBy(Color), sum(StandardCost), columnNaming: '$N$V', lateral: true) ~> PivotColorStandardCost"
			},
			{
				"name": "ProductSourceBranch",
				"script": "ProductSource select()~> ProductSourceBranch"
			},
			{
				"name": "Join1",
				"script": "PivotColorStandardCost, ProductSourceBranch join(ProductID == ProductID,joinType:'inner',broadcast: 'none')~> Join1"
			}
		]
	}
}